pyproject.toml
df_lib/__about__.py
df_lib/__init__.py
df_lib/datastruct.py
df_lib/map_struct.py
test/conftest.py
test/test_basic_map_pack_unpack.py
df_lib-0.3.1.dist-info/METADATA
df_lib-0.3.1.dist-info/WHEEL
df_lib-0.3.1.dist-info/RECORD
