Metadata-Version: 2.4
Name: df_lib
Version: 0.3.1
Summary: Desolate Frontiers helper library
Project-URL: Documentation, https://github.com/OoriData/df_lib
Project-URL: Issues, https://github.com/OoriData/df_lib/issues
Project-URL: Source, https://github.com/OoriData/df_lib/tree/main
Author-email: Osi Ogbuji <osi@oori.dev>, Uche Ogbuji <uche@oori.dev>, Aidan Reese <aidan@oori.dev>, Jide Ogbuji <jide@oori.dev>, Udoka Ogbuji <udoka@oori.dev>
License-Expression: LicenseRef-Proprietary
Classifier: Development Status :: 4 - Beta
Classifier: Programming Language :: Python
Classifier: Programming Language :: Python :: 3.10
Classifier: Programming Language :: Python :: 3.11
Classifier: Programming Language :: Python :: 3.12
Classifier: Programming Language :: Python :: Implementation :: CPython
Classifier: Programming Language :: Python :: Implementation :: PyPy
Requires-Python: >=3.12
Requires-Dist: pytest
